{"chord":
    {
        "value": {
            "type": "string",
            "pattern": "^((N)|(([A-G](b*|#*))((:(maj|min|dim|aug|maj7|min7|7|dim7|hdim7|minmaj7|maj6|min6|9|maj9|min9|sus4|sus2|1|5|13)(\\((\\*?([b#]*([1-9]|1[0-3]?))(,\\*?([b#]*([1-9]|1[0-3]?)))*)\\))?)|(:\\((\\*?([b#]*([1-9]|1[0-3]?))(,\\*?([b#]*([1-9]|1[0-3]?)))*)\\)))?((/([b#]*([1-9]|1[0-3]?)))?)?))$"
        },
        "dense": false,
        "description": "Expanded chord set from chord_harte.  Includes sus2, 1, 5, and 13."
    }
}
